mylib/__init__.py
mylib/get_hugging_face_embeding.py
mylib/plotverse_xr_llm.py
mylib/streamlit.py
LlmEmbeddingXrVizualization-1.1.2.dist-info/LICENSE
LlmEmbeddingXrVizualization-1.1.2.dist-info/METADATA
LlmEmbeddingXrVizualization-1.1.2.dist-info/WHEEL
LlmEmbeddingXrVizualization-1.1.2.dist-info/entry_points.txt
LlmEmbeddingXrVizualization-1.1.2.dist-info/top_level.txt
LlmEmbeddingXrVizualization-1.1.2.dist-info/RECORD
