Metadata-Version: 2.1
Name: LlmEmbeddingXrVizualization
Version: 1.1.2
Summary: A package for visualizing embeddings spaces from Hugging Face models
Home-page: https://github.com/rmr327/LlmEmbeddingXrVizualization
Author: Rakeen Rouf & Akalpit
Author-email: rakeenrouf@gmail.com
License: UNKNOWN
Platform: UNKNOWN
Classifier: Programming Language :: Python :: 3
Classifier: License :: OSI Approved :: MIT License
Classifier: Operating System :: OS Independent
Requires-Python: >=3.6
License-File: LICENSE
Requires-Dist: Cython<4.0.0,>=3.0.11
Requires-Dist: Jinja2<4.0.0,>=3.1.3
Requires-Dist: MarkupSafe<3.0.0,>=2.1.5
Requires-Dist: PyYAML<7.0.0,>=6.0.2
Requires-Dist: bpy<5.0.0,>=3.0.0
Requires-Dist: certifi<2025.0.0,>=2024.8.30
Requires-Dist: charset-normalizer<4.0.0,>=3.4.0
Requires-Dist: click<9.0.0,>=8.1.7
Requires-Dist: contourpy<2.0.0,>=1.3.1
Requires-Dist: cycler<1.0.0,>=0.12.1
Requires-Dist: exceptiongroup<2.0.0,>=1.2.2
Requires-Dist: filelock<4.0.0,>=3.13.1
Requires-Dist: fonttools<5.0.0,>=4.55.0
Requires-Dist: fsspec<2025.0.0,>=2024.2.0
Requires-Dist: huggingface-hub<1.0.0,>=0.26.3
Requires-Dist: idna<4.0.0,>=3.10
Requires-Dist: iniconfig<3.0.0,>=2.0.0
Requires-Dist: joblib<2.0.0,>=1.4.2
Requires-Dist: kaleido
Requires-Dist: kiwisolver<2.0.0,>=1.4.7
Requires-Dist: llvmlite<1.0.0,>=0.43.0
Requires-Dist: mathutils<4.0.0,>=3.3.0
Requires-Dist: matplotlib<4.0.0,>=3.9.3
Requires-Dist: mpmath<2.0.0,>=1.3.0
Requires-Dist: networkx<4.0.0,>=3.2.1
Requires-Dist: numba<1.0.0,>=0.60.0
Requires-Dist: numpy<2.0.0,>=1.26.3
Requires-Dist: packaging<25.0,>=24.2
Requires-Dist: pandas<3.0.0,>=2.2.3
Requires-Dist: pillow<11.0.0,>=10.2.0
Requires-Dist: plotly<6.0.0,>=5.24.1
Requires-Dist: pluggy<2.0.0,>=1.5.0
Requires-Dist: pynndescent<1.0.0,>=0.5.13
Requires-Dist: pyparsing<4.0.0,>=3.2.0
Requires-Dist: pytest<9.0.0,>=8.3.3
Requires-Dist: python-dateutil<3.0.0,>=2.9.0.post0
Requires-Dist: pytz<2025.0,>=2024.2
Requires-Dist: regex<2025.0.0,>=2024.11.6
Requires-Dist: requests<3.0.0,>=2.32.3
Requires-Dist: safetensors<1.0.0,>=0.4.5
Requires-Dist: scikit-learn<2.0.0,>=1.5.2
Requires-Dist: scipy<2.0.0,>=1.14.1
Requires-Dist: six<2.0.0,>=1.16.0
Requires-Dist: sympy<2.0.0,>=1.13.1
Requires-Dist: tenacity<10.0.0,>=9.0.0
Requires-Dist: threadpoolctl<4.0.0,>=3.5.0
Requires-Dist: tokenizers<1.0.0,>=0.20.3
Requires-Dist: tomli<3.0.0,>=2.2.1
Requires-Dist: torch
Requires-Dist: torchaudio
Requires-Dist: torchvision
Requires-Dist: tqdm<5.0.0,>=4.67.1
Requires-Dist: transformers<5.0.0,>=4.46.3
Requires-Dist: typing-extensions<5.0.0,>=4.9.0
Requires-Dist: tzdata<2025.0,>=2024.2
Requires-Dist: umap-learn<1.0.0,>=0.5.6
Requires-Dist: urllib3<3.0.0,>=2.2.3
Requires-Dist: zstandard<1.0.0,>=0.23.0
